<?xml version="1.0" encoding="utf-8"?>
<Font size="64" family="Inconsolata" height="125" style="Medium">
 <Char width="60" offset="0 95" rect="1 81 0 0" code=" "/>
 <Char width="60" offset="21 16" rect="2 2 18 81" code="!"/>
 <Char width="60" offset="12 16" rect="21 2 39 33" code="&quot;"/>
 <Char width="60" offset="2 20" rect="61 6 59 74" code="#"/>
 <Char width="60" offset="6 18" rect="121 4 53 83" code="$"/>
 <Char width="60" offset="3 19" rect="175 5 59 78" code="%"/>
 <Char width="60" offset="4 20" rect="235 6 58 78" code="&amp;"/>
 <Char width="60" offset="24 16" rect="294 2 18 33" code="'"/>
 <Char width="60" offset="16 15" rect="313 1 39 101" code="("/>
 <Char width="60" offset="8 15" rect="353 1 39 101" code=")"/>
 <Char width="60" offset="4 33" rect="393 19 55 51" code="*"/>
 <Char width="60" offset="5 32" rect="449 18 53 52" code="+"/>
 <Char width="60" offset="18 80" rect="503 66 22 35" code=","/>
 <Char width="60" offset="8 52" rect="526 38 47 12" code="-"/>
 <Char width="60" offset="21 80" rect="574 66 18 17" code="."/>
 <Char width="60" offset="7 15" rect="593 1 50 86" code="/"/>
 <Char width="60" offset="6 20" rect="644 6 52 77" code="0"/>
 <Char width="60" offset="10 21" rect="697 7 43 75" code="1"/>
 <Char width="60" offset="8 20" rect="741 6 48 75" code="2"/>
 <Char width="60" offset="7 20" rect="790 6 48 77" code="3"/>
 <Char width="60" offset="5 21" rect="839 7 53 74" code="4"/>
 <Char width="60" offset="7 21" rect="893 7 50 76" code="5"/>
 <Char width="60" offset="8 20" rect="944 6 48 77" code="6"/>
 <Char width="60" offset="9 21" rect="1 108 46 74" code="7"/>
 <Char width="60" offset="7 20" rect="48 107 50 77" code="8"/>
 <Char width="60" offset="8 20" rect="99 107 48 77" code="9"/>
 <Char width="60" offset="21 43" rect="148 130 18 54" code=":"/>
 <Char width="60" offset="18 43" rect="167 130 22 72" code=";"/>
 <Char width="60" offset="4 26" rect="190 113 55 65" code="&lt;"/>
 <Char width="60" offset="5 42" rect="246 129 53 34" code="="/>
 <Char width="60" offset="4 26" rect="300 113 56 65" code=">"/>
 <Char width="60" offset="7 16" rect="357 103 49 81" code="?"/>
 <Char width="60" offset="3 20" rect="407 107 57 77" code="@"/>
 <Char width="60" offset="1 19" rect="465 106 61 77" code="A"/>
 <Char width="60" offset="5 21" rect="527 108 53 74" code="B"/>
 <Char width="60" offset="4 20" rect="581 107 56 77" code="C"/>
 <Char width="60" offset="6 21" rect="638 108 53 75" code="D"/>
 <Char width="60" offset="7 21" rect="692 108 50 74" code="E"/>
 <Char width="60" offset="9 21" rect="743 108 47 74" code="F"/>
 <Char width="60" offset="4 20" rect="791 107 55 77" code="G"/>
 <Char width="60" offset="6 21" rect="847 108 52 75" code="H"/>
 <Char width="60" offset="9 21" rect="900 108 43 75" code="I"/>
 <Char width="60" offset="5 21" rect="944 108 53 76" code="J"/>
 <Char width="60" offset="5 20" rect="1 208 57 76" code="K"/>
 <Char width="60" offset="7 21" rect="59 209 49 75" code="L"/>
 <Char width="60" offset="4 21" rect="109 209 55 75" code="M"/>
 <Char width="60" offset="6 21" rect="165 209 52 75" code="N"/>
 <Char width="60" offset="3 20" rect="218 208 57 77" code="O"/>
 <Char width="60" offset="7 21" rect="276 209 51 74" code="P"/>
 <Char width="60" offset="3 20" rect="328 208 57 92" code="Q"/>
 <Char width="60" offset="6 21" rect="386 209 54 74" code="R"/>
 <Char width="60" offset="5 20" rect="441 208 53 77" code="S"/>
 <Char width="60" offset="3 21" rect="495 209 56 75" code="T"/>
 <Char width="60" offset="6 21" rect="552 209 52 76" code="U"/>
 <Char width="60" offset="2 21" rect="605 209 60 75" code="V"/>
 <Char width="60" offset="1 21" rect="666 209 61 75" code="W"/>
 <Char width="60" offset="3 21" rect="728 209 58 74" code="X"/>
 <Char width="60" offset="2 21" rect="787 209 59 74" code="Y"/>
 <Char width="60" offset="6 21" rect="847 209 53 75" code="Z"/>
 <Char width="60" offset="15 15" rect="901 203 39 91" code="["/>
 <Char width="60" offset="7 15" rect="941 203 50 86" code="\"/>
 <Char width="60" offset="9 15" rect="1 301 39 91" code="]"/>
 <Char width="60" offset="10 21" rect="41 307 43 36" code="^"/>
 <Char width="60" offset="4 94" rect="85 380 56 11" code="_"/>
 <Char width="60" offset="16 15" rect="142 301 26 32" code="`"/>
 <Char width="60" offset="5 38" rect="169 324 51 59" code="a"/>
 <Char width="60" offset="7 16" rect="221 302 52 81" code="b"/>
 <Char width="60" offset="6 38" rect="274 324 53 59" code="c"/>
 <Char width="60" offset="5 16" rect="328 302 53 81" code="d"/>
 <Char width="60" offset="5 38" rect="382 324 52 59" code="e"/>
 <Char width="60" offset="7 15" rect="435 301 55 80" code="f"/>
 <Char width="60" offset="4 38" rect="491 324 57 77" code="g"/>
 <Char width="60" offset="8 16" rect="549 302 48 79" code="h"/>
 <Char width="60" offset="12 17" rect="598 303 39 78" code="i"/>
 <Char width="60" offset="5 17" rect="638 303 45 98" code="j"/>
 <Char width="60" offset="7 16" rect="684 302 56 80" code="k"/>
 <Char width="60" offset="9 16" rect="741 302 45 79" code="l"/>
 <Char width="60" offset="4 38" rect="787 324 56 58" code="m"/>
 <Char width="60" offset="8 38" rect="844 324 47 57" code="n"/>
 <Char width="60" offset="4 38" rect="892 324 55 59" code="o"/>
 <Char width="60" offset="7 38" rect="948 324 52 76" code="p"/>
 <Char width="60" offset="5 38" rect="1 423 52 76" code="q"/>
 <Char width="60" offset="11 38" rect="54 423 48 58" code="r"/>
 <Char width="60" offset="6 38" rect="103 423 50 59" code="s"/>
 <Char width="60" offset="8 24" rect="154 409 49 73" code="t"/>
 <Char width="60" offset="7 40" rect="204 425 50 57" code="u"/>
 <Char width="60" offset="3 40" rect="255 425 56 56" code="v"/>
 <Char width="60" offset="1 40" rect="312 425 61 56" code="w"/>
 <Char width="60" offset="4 40" rect="374 425 56 55" code="x"/>
 <Char width="60" offset="2 40" rect="431 425 58 75" code="y"/>
 <Char width="60" offset="6 40" rect="490 425 52 56" code="z"/>
 <Char width="60" offset="6 19" rect="543 404 47 95" code="{"/>
 <Char width="60" offset="26 17" rect="591 402 12 96" code="|"/>
 <Char width="60" offset="11 19" rect="604 404 46 95" code="}"/>
 <Char width="60" offset="4 39" rect="651 424 57 20" code="~"/>
</Font>
